cameo_rank
