Metadata-Version: 2.1
Name: cameo-rank
Version: 0.1.1
Summary: A Python package for managing game rankings using FastAPI.
Home-page: https://github.com/JcXGTcW/cameo_rank
Author: JcXGTcW
Author-email: jcxgtcw@gmail.com
Classifier: Programming Language :: Python :: 3.8
Classifier: License :: OSI Approved :: MIT License
Classifier: Operating System :: OS Independent
Requires-Python: >=3.8
Provides-Extra: dev
License-File: LICENSE
